src/__init__.py
src/main.py
virusdata-1.0.dist-info/LICENSE.txt
virusdata-1.0.dist-info/METADATA
virusdata-1.0.dist-info/WHEEL
virusdata-1.0.dist-info/entry_points.txt
virusdata-1.0.dist-info/top_level.txt
virusdata-1.0.dist-info/RECORD
